{
    "schemaVersion": 2,
    "mediaType": "application/vnd.docker.distribution.manifest.list.v2+json",
    "manifests": [
        {
            "digest": "sha256:7e57290c42ce71c9171237eb0d082c99b036d819a9d6c8d3834b194da96736b9",
            "mediaType": "application/vnd.docker.distribution.manifest.v2+json",
            "platform": {
                "architecture": "amd64",
                "os": "linux"
            },
            "size": 1377
        },
        {
            "digest": "sha256:8203a9192ea844c6cb0f1f395cd6baa1f8db1c36605c92ca4392a817bcfaf81d",
            "mediaType": "application/vnd.docker.distribution.manifest.v2+json",
            "platform": {
                "architecture": "arm",
                "os": "linux",
                "variant": "v7"
            },
            "size": 1376
        },
        {
            "digest": "sha256:be6c1d2f454203f1b0f89fe71252609782914f2514a74667f37e45d8716f035f",
            "mediaType": "application/vnd.docker.distribution.manifest.v2+json",
            "platform": {
                "architecture": "arm64",
                "os": "linux",
                "variant": "v8"
            },
            "size": 1377
        },
        {
            "digest": "sha256:6d433d16f708ad267959275fdf964f70aa76df9700a3383ed22b11b5610ff3d1",
            "mediaType": "application/vnd.docker.distribution.manifest.v2+json",
            "platform": {
                "architecture": "386",
                "os": "linux"
            },
            "size": 1377
        }
    ]
}