{
    "schemaVersion": 2,
    "mediaType": "application/vnd.docker.distribution.manifest.list.v2+json",
    "manifests": [
        {
            "digest": "sha256:b0221cd1aada1ff9f37fcdf9b4a7f76f00b7167c28c14d915b056f08fd1700e4",
            "mediaType": "application/vnd.docker.distribution.manifest.v2+json",
            "platform": {
                "architecture": "amd64",
                "os": "linux"
            },
            "size": 1376
        },
        {
            "digest": "sha256:adaad51199713991097cadd5ac0e143e16b4488e92690b9fddc2e202e19d6154",
            "mediaType": "application/vnd.docker.distribution.manifest.v2+json",
            "platform": {
                "architecture": "arm",
                "os": "linux",
                "variant": "v5"
            },
            "size": 1376
        },
        {
            "digest": "sha256:a4678f985bc7bf4716a46792775ac1a164064e0c1609eff961f18181b804c4c4",
            "mediaType": "application/vnd.docker.distribution.manifest.v2+json",
            "platform": {
                "architecture": "arm",
                "os": "linux",
                "variant": "v7"
            },
            "size": 1376
        },
        {
            "digest": "sha256:709cb7b79b637d2257df1a06700bd69d1d210d6cccd743af3e0470ba5f78e106",
            "mediaType": "application/vnd.docker.distribution.manifest.v2+json",
            "platform": {
                "architecture": "arm64",
                "os": "linux",
                "variant": "v8"
            },
            "size": 1376
        },
        {
            "digest": "sha256:04fa2c77258c56d5a90e6117c2ff2d82c14d345ee9637841e1a0f9d123644fe7",
            "mediaType": "application/vnd.docker.distribution.manifest.v2+json",
            "platform": {
                "architecture": "386",
                "os": "linux"
            },
            "size": 1377
        },
        {
            "digest": "sha256:7c4e015c74e61a602f9791813e63176cf3e68601401640b2dd06fcda03d0f892",
            "mediaType": "application/vnd.docker.distribution.manifest.v2+json",
            "platform": {
                "architecture": "mips64le",
                "os": "linux"
            },
            "size": 1377
        },
        {
            "digest": "sha256:1faa0ac7ecab32083e879739f3d09a1b115325e4d1821b992e802a42d9c813d4",
            "mediaType": "application/vnd.docker.distribution.manifest.v2+json",
            "platform": {
                "architecture": "ppc64le",
                "os": "linux"
            },
            "size": 1377
        },
        {
            "digest": "sha256:d0937b29c40ef0f950db83c0c256cf99e11985650dd4f61c1248b830edeeb134",
            "mediaType": "application/vnd.docker.distribution.manifest.v2+json",
            "platform": {
                "architecture": "s390x",
                "os": "linux"
            },
            "size": 1376
        }
    ]
}