{
    "schemaVersion": 2,
    "mediaType": "application/vnd.oci.image.index.v1+json",
    "manifests": [
        {
            "digest": "sha256:33d782143e3a76315de8570db1673fda6d5b17c854190b74e9e890d8e95c85cf",
            "mediaType": "application/vnd.oci.image.manifest.v1+json",
            "platform": {
                "architecture": "amd64",
                "os": "linux"
            },
            "size": 424
        },
        {
            "digest": "sha256:b94e236b9fdac3af61b909ac8326f6cdce01182a043d6e349d1d21026b5293dc",
            "mediaType": "application/vnd.oci.image.manifest.v1+json",
            "platform": {
                "architecture": "unknown",
                "os": "unknown"
            },
            "size": 562
        },
        {
            "digest": "sha256:68cb2a5db09cfdaaa63fe1aa3b2efe024ca88df6c8da5d4eb5e96d45a05ea6cb",
            "mediaType": "application/vnd.oci.image.manifest.v1+json",
            "platform": {
                "architecture": "arm",
                "os": "linux",
                "variant": "v7"
            },
            "size": 424
        },
        {
            "digest": "sha256:ecda8394a012c3885cedabb62ef0cc6cc5646b1cc2e75e353baf2455b3a1e9a5",
            "mediaType": "application/vnd.oci.image.manifest.v1+json",
            "platform": {
                "architecture": "unknown",
                "os": "unknown"
            },
            "size": 562
        },
        {
            "digest": "sha256:23fdb0648173966ac0b863e5b3d63032e99f44533c5b396e62f29770ca2c5210",
            "mediaType": "application/vnd.oci.image.manifest.v1+json",
            "platform": {
                "architecture": "arm64",
                "os": "linux",
                "variant": "v8"
            },
            "size": 424
        },
        {
            "digest": "sha256:0ed4dde5d76fff27d1efd6a0caf406a1d843b2e0d81ad841181acf698302d0aa",
            "mediaType": "application/vnd.oci.image.manifest.v1+json",
            "platform": {
                "architecture": "unknown",
                "os": "unknown"
            },
            "size": 562
        },
        {
            "digest": "sha256:680c945d273526b50e21a023a4dc14aecefa310bb53cb4420a686a254091dc77",
            "mediaType": "application/vnd.oci.image.manifest.v1+json",
            "platform": {
                "architecture": "ppc64le",
                "os": "linux"
            },
            "size": 424
        },
        {
            "digest": "sha256:eba541a8bd5d87299e360ae932e4ecd47ba1f2ff4d458870579176f30de5b44d",
            "mediaType": "application/vnd.oci.image.manifest.v1+json",
            "platform": {
                "architecture": "unknown",
                "os": "unknown"
            },
            "size": 562
        },
        {
            "digest": "sha256:898332afc4624715fbfa02588229a452de3fa99c10930badd850af68c974c947",
            "mediaType": "application/vnd.oci.image.manifest.v1+json",
            "platform": {
                "architecture": "riscv64",
                "os": "linux"
            },
            "size": 424
        },
        {
            "digest": "sha256:813d95ee220e7f452c839aa74fe26213031a7f21919133e51daeb49add610c69",
            "mediaType": "application/vnd.oci.image.manifest.v1+json",
            "platform": {
                "architecture": "unknown",
                "os": "unknown"
            },
            "size": 562
        },
        {
            "digest": "sha256:bc3e62fd633253e03be50d73a6493d3cc9834065bba4e88bc0ad06b312502a22",
            "mediaType": "application/vnd.oci.image.manifest.v1+json",
            "platform": {
                "architecture": "s390x",
                "os": "linux"
            },
            "size": 424
        },
        {
            "digest": "sha256:c525a9150fbfe172e3d0ace43f8c202c1104630793f4ebdfb9c1aa1466163293",
            "mediaType": "application/vnd.oci.image.manifest.v1+json",
            "platform": {
                "architecture": "unknown",
                "os": "unknown"
            },
            "size": 562
        }
    ]
}