{
    "schemaVersion": 2,
    "mediaType": "application/vnd.oci.image.index.v1+json",
    "manifests": [
        {
            "digest": "sha256:364d3f277f79b11fafee2f44e8198054486583d3392e2472eb656d5c780156f5",
            "mediaType": "application/vnd.oci.image.manifest.v1+json",
            "platform": {
                "architecture": "amd64",
                "os": "linux"
            },
            "size": 1021
        },
        {
            "digest": "sha256:159297451584dc283cd8a7a56373c77c1057e606254abdce125f0fb4ca0555b0",
            "mediaType": "application/vnd.oci.image.manifest.v1+json",
            "platform": {
                "architecture": "unknown",
                "os": "unknown"
            },
            "size": 562
        },
        {
            "digest": "sha256:38c45bfd369cb16e2698392223e8dff7dc054055a5e32f6a53e562ed49d9217e",
            "mediaType": "application/vnd.oci.image.manifest.v1+json",
            "platform": {
                "architecture": "arm",
                "os": "linux",
                "variant": "v5"
            },
            "size": 1041
        },
        {
            "digest": "sha256:9070c0319380abf6e4599a7a7fa5c685a156a611c88371070e4edd19d8ea5910",
            "mediaType": "application/vnd.oci.image.manifest.v1+json",
            "platform": {
                "architecture": "unknown",
                "os": "unknown"
            },
            "size": 562
        },
        {
            "digest": "sha256:bcfd043db5f7fc25b21c19725d62f573676bb4a2ac327576cf337c86fbba461c",
            "mediaType": "application/vnd.oci.image.manifest.v1+json",
            "platform": {
                "architecture": "arm",
                "os": "linux",
                "variant": "v7"
            },
            "size": 1041
        },
        {
            "digest": "sha256:cf2086a3e83f899d09c0dc56bd8749615d70331ba2251ddaa1559758485b26e5",
            "mediaType": "application/vnd.oci.image.manifest.v1+json",
            "platform": {
                "architecture": "unknown",
                "os": "unknown"
            },
            "size": 562
        },
        {
            "digest": "sha256:f41950d5d084b96ee49ad4c872319f5afce6667bcc99b6bb318df03cd0621ad6",
            "mediaType": "application/vnd.oci.image.manifest.v1+json",
            "platform": {
                "architecture": "arm64",
                "os": "linux",
                "variant": "v8"
            },
            "size": 1041
        },
        {
            "digest": "sha256:25ff35601c2b48fde8f6de6927469d123d8e224dcbb5593a97e1a3f93f548eef",
            "mediaType": "application/vnd.oci.image.manifest.v1+json",
            "platform": {
                "architecture": "unknown",
                "os": "unknown"
            },
            "size": 562
        },
        {
            "digest": "sha256:d95e820da87ce5b36b08104e48551cd4847a0d87b90dcc8d351af1a602ce6308",
            "mediaType": "application/vnd.oci.image.manifest.v1+json",
            "platform": {
                "architecture": "386",
                "os": "linux"
            },
            "size": 1017
        },
        {
            "digest": "sha256:c83a7a20030d5ea33f8bcadc85210882c9b2c77e89d586cb260849e0e2d64962",
            "mediaType": "application/vnd.oci.image.manifest.v1+json",
            "platform": {
                "architecture": "unknown",
                "os": "unknown"
            },
            "size": 562
        },
        {
            "digest": "sha256:7e19118bdfaff2b35a839e5bd438cd2125f80ed2f75f289a80e58d969c6371ca",
            "mediaType": "application/vnd.oci.image.manifest.v1+json",
            "platform": {
                "architecture": "mips64le",
                "os": "linux"
            },
            "size": 1029
        },
        {
            "digest": "sha256:6ac4d21d3cd42c777b012f04a3e1c017d2ae4bc6196a4951d487394e7d7f44e9",
            "mediaType": "application/vnd.oci.image.manifest.v1+json",
            "platform": {
                "architecture": "ppc64le",
                "os": "linux"
            },
            "size": 1029
        },
        {
            "digest": "sha256:745469758c1778e2c2c6db3552c4210e9014728af1afae9b670ddef7c75634d8",
            "mediaType": "application/vnd.oci.image.manifest.v1+json",
            "platform": {
                "architecture": "unknown",
                "os": "unknown"
            },
            "size": 562
        },
        {
            "digest": "sha256:385fb99ea590df68b1d3938018828651e66c6a51957f598aa136ffbf2aad323d",
            "mediaType": "application/vnd.oci.image.manifest.v1+json",
            "platform": {
                "architecture": "s390x",
                "os": "linux"
            },
            "size": 1021
        },
        {
            "digest": "sha256:f6ae02b16a33452d274d28b347f3c65bc3c6dfa3eed0d83d14584ab7f1057b6b",
            "mediaType": "application/vnd.oci.image.manifest.v1+json",
            "platform": {
                "architecture": "unknown",
                "os": "unknown"
            },
            "size": 562
        }
    ]
}