{
    "schemaVersion": 2,
    "mediaType": "application/vnd.oci.image.index.v1+json",
    "manifests": [
        {
            "digest": "sha256:238da73d5f7e26f01b30f1e30b4a7156d3b344d9368c278ef5bd14d2294f27f6",
            "mediaType": "application/vnd.oci.image.manifest.v1+json",
            "platform": {
                "architecture": "amd64",
                "os": "linux"
            },
            "size": 1021
        },
        {
            "digest": "sha256:0967a712b5de32e407572c07ce6019a6a572f05ac7661e708b3f08753dcac9fd",
            "mediaType": "application/vnd.oci.image.manifest.v1+json",
            "platform": {
                "architecture": "unknown",
                "os": "unknown"
            },
            "size": 840
        },
        {
            "digest": "sha256:22ab670a3016ac3584014e8b913f05d8b003b2a99a45bb908a65b33d93170e5d",
            "mediaType": "application/vnd.oci.image.manifest.v1+json",
            "platform": {
                "architecture": "arm64",
                "os": "linux",
                "variant": "v8"
            },
            "size": 1023
        },
        {
            "digest": "sha256:433c455526dd76f85231cf75de3b4ee0181ffa61af7a36bd25391cde5528b2fe",
            "mediaType": "application/vnd.oci.image.manifest.v1+json",
            "platform": {
                "architecture": "unknown",
                "os": "unknown"
            },
            "size": 840
        }
    ]
}