{
    "schemaVersion": 2,
    "mediaType": "application/vnd.docker.distribution.manifest.v2+json",
    "config": {
        "mediaType": "application/vnd.docker.container.image.v1+json",
        "size": 2554,
        "digest": "sha256:d6f5f4c579c44f0cd8f0307a80ce9a470e1ecd1660420297715fb74bc28d1d12"
    },
    "layers": [
        {
            "mediaType": "application/vnd.docker.image.rootfs.diff.tar.gzip",
            "size": 105034460,
            "digest": "sha256:daf71fff6ad23e171d2f7a3ab8fe3656349b54fc2eb1d3808e067534d6336d0d"
        },
        {
            "mediaType": "application/vnd.docker.image.rootfs.diff.tar.gzip",
            "size": 87991,
            "digest": "sha256:9565f3700e9dcc3c74d260493eb0e0c0504f776745a8d9374c2c23a026672df1"
        },
        {
            "mediaType": "application/vnd.docker.image.rootfs.diff.tar.gzip",
            "size": 417,
            "digest": "sha256:3d725258869657edded838e7555704873ca4547bb7a92e505efee2e8e3a15206"
        },
        {
            "mediaType": "application/vnd.docker.image.rootfs.diff.tar.gzip",
            "size": 2592578,
            "digest": "sha256:ca57dfa5425bbe0f80b53bb61c76041aa08a6dfad51e32698fbd67206120cb1e"
        }
    ]
}