{
    "schemaVersion": 2,
    "mediaType": "application/vnd.docker.distribution.manifest.v2+json",
    "config": {
        "mediaType": "application/vnd.docker.container.image.v1+json",
        "size": 2554,
        "digest": "sha256:46016ef7a5597f2ccae497ba80d0d5e590abbca12ca9a61fc6abc1f8e0c7063c"
    },
    "layers": [
        {
            "mediaType": "application/vnd.docker.image.rootfs.diff.tar.gzip",
            "size": 104682272,
            "digest": "sha256:272e9a376206fe45c602948892e1956511de2a9a71e2dd6491c8c9e7d6b64819"
        },
        {
            "mediaType": "application/vnd.docker.image.rootfs.diff.tar.gzip",
            "size": 85932,
            "digest": "sha256:929c5ff55e1a8cd0426b9ba93ba388df67f18dd252330963d82fe2e1a0984212"
        },
        {
            "mediaType": "application/vnd.docker.image.rootfs.diff.tar.gzip",
            "size": 417,
            "digest": "sha256:02f32ead25cec87fe01c2ff41558241e9c6a6c3e79f29e8f87f660e71d64905f"
        },
        {
            "mediaType": "application/vnd.docker.image.rootfs.diff.tar.gzip",
            "size": 2404593,
            "digest": "sha256:072730bdc14dcc7275f5c0d3308c68c0c4826f70118d9c2214b7010c4b4e4122"
        }
    ]
}