{
    "schemaVersion": 2,
    "mediaType": "application/vnd.docker.distribution.manifest.v2+json",
    "config": {
        "mediaType": "application/vnd.docker.container.image.v1+json",
        "size": 2554,
        "digest": "sha256:22bc1db590a4a180cdc9ff82eb2830860a141a73737ced90d7533cc784db5b13"
    },
    "layers": [
        {
            "mediaType": "application/vnd.docker.image.rootfs.diff.tar.gzip",
            "size": 105031549,
            "digest": "sha256:7515bf1ca88cf19d6ca0e16fe7fc8f025ccc2725391135439aaa9947aa5fc41f"
        },
        {
            "mediaType": "application/vnd.docker.image.rootfs.diff.tar.gzip",
            "size": 87986,
            "digest": "sha256:0874e5aa454d33cd5c006781aa692daa4c03f4021bbf8544c1cd13042d251af8"
        },
        {
            "mediaType": "application/vnd.docker.image.rootfs.diff.tar.gzip",
            "size": 416,
            "digest": "sha256:8ded874fce7f73b8dfed103c908128fd78193694e4dd83988dd1e4ba91b36cd6"
        },
        {
            "mediaType": "application/vnd.docker.image.rootfs.diff.tar.gzip",
            "size": 2676233,
            "digest": "sha256:c95d9693c3e44862c9757c55b9ced6dcc4e005bfef66fc873ff644a744105684"
        }
    ]
}