{
    "schemaVersion": 2,
    "mediaType": "application/vnd.docker.distribution.manifest.v2+json",
    "config": {
        "mediaType": "application/vnd.docker.container.image.v1+json",
        "size": 2554,
        "digest": "sha256:89086778f6b4c10fb39210533224f62840f4b93ab3b3e9e09cb86ca706d7dcbe"
    },
    "layers": [
        {
            "mediaType": "application/vnd.docker.image.rootfs.diff.tar.gzip",
            "size": 100803233,
            "digest": "sha256:087b6dcbec25ec1cbc730f29ed11257f5b0cc3eb3e575a587358ced4e48e8e89"
        },
        {
            "mediaType": "application/vnd.docker.image.rootfs.diff.tar.gzip",
            "size": 81600,
            "digest": "sha256:3cccc9beb695b9def2938918aec97e531fe192fa7b6b7dbd217d7b2f97eeeace"
        },
        {
            "mediaType": "application/vnd.docker.image.rootfs.diff.tar.gzip",
            "size": 416,
            "digest": "sha256:8417110045e22fb5a737034e753028240b1d31bdf81a7a5b2b3e87739df1a084"
        },
        {
            "mediaType": "application/vnd.docker.image.rootfs.diff.tar.gzip",
            "size": 2298831,
            "digest": "sha256:1418415b0a5dee47572cce73a4d3e2f2b53c4d236d28c472a3963f6a5bb00816"
        }
    ]
}