{
    "schemaVersion": 2,
    "mediaType": "application/vnd.docker.distribution.manifest.v2+json",
    "config": {
        "mediaType": "application/vnd.docker.container.image.v1+json",
        "size": 2554,
        "digest": "sha256:80a1096c0bff8303bd479d1224899c6d169d0eaf220ac395afda98f71b8a375c"
    },
    "layers": [
        {
            "mediaType": "application/vnd.docker.image.rootfs.diff.tar.gzip",
            "size": 104926655,
            "digest": "sha256:299668a79b8add698f8396eda6413971b0a555ba3ae46e38e2e70c0874e09449"
        },
        {
            "mediaType": "application/vnd.docker.image.rootfs.diff.tar.gzip",
            "size": 88358,
            "digest": "sha256:98cadcf2f8195b8d51bce920b58dcb00fb5bdcd25eba52c19b63291eb0356357"
        },
        {
            "mediaType": "application/vnd.docker.image.rootfs.diff.tar.gzip",
            "size": 418,
            "digest": "sha256:46896d1154b1c6ed1f258ad61e6d72fabde660c366f52ed99b10c00cd5b07640"
        },
        {
            "mediaType": "application/vnd.docker.image.rootfs.diff.tar.gzip",
            "size": 2511712,
            "digest": "sha256:79a77e7c1be9a2c4f77ead609e8d8b7162377bb6905b2a244c7964d74d8c8762"
        }
    ]
}