{
    "schemaVersion": 2,
    "mediaType": "application/vnd.docker.distribution.manifest.v2+json",
    "config": {
        "mediaType": "application/vnd.docker.container.image.v1+json",
        "size": 2554,
        "digest": "sha256:72710060bfd6c1bd99fe60381c7cf33721299d8f3e74f7452df3645e56d2c664"
    },
    "layers": [
        {
            "mediaType": "application/vnd.docker.image.rootfs.diff.tar.gzip",
            "size": 104934411,
            "digest": "sha256:395d6cac9d1e6bbf06013cbdd94147eb2dc34bca4a6c7cfedd5f2bbdfa181245"
        },
        {
            "mediaType": "application/vnd.docker.image.rootfs.diff.tar.gzip",
            "size": 88355,
            "digest": "sha256:2b0eb359b4e3fe0f0e24115f5707598ff0a61aafd705267f04a40f9c0d031605"
        },
        {
            "mediaType": "application/vnd.docker.image.rootfs.diff.tar.gzip",
            "size": 416,
            "digest": "sha256:3757569bf538e46771f24220ee9adbf1b5b911e5e625b87688a2cd553bc99004"
        },
        {
            "mediaType": "application/vnd.docker.image.rootfs.diff.tar.gzip",
            "size": 2582258,
            "digest": "sha256:2a9f1ae020e1174089186c85e75fdd02adc9b21031f42edd009f1b66a1f739e5"
        }
    ]
}