{
    "schemaVersion": 2,
    "mediaType": "application/vnd.docker.distribution.manifest.v2+json",
    "config": {
        "mediaType": "application/vnd.docker.container.image.v1+json",
        "size": 2554,
        "digest": "sha256:7f4efe2c7166a764f8789732c1f906de26dc2301be47e86f5a13a01724728a48"
    },
    "layers": [
        {
            "mediaType": "application/vnd.docker.image.rootfs.diff.tar.gzip",
            "size": 100755311,
            "digest": "sha256:4c85a9186b09a843552e661bb3f917ffc43fdda27de1d3c41207f3bd4492b315"
        },
        {
            "mediaType": "application/vnd.docker.image.rootfs.diff.tar.gzip",
            "size": 74986,
            "digest": "sha256:285c781b43037579a40d13d0acf8a5cde18743536411c5e7b8f93483030a6964"
        },
        {
            "mediaType": "application/vnd.docker.image.rootfs.diff.tar.gzip",
            "size": 417,
            "digest": "sha256:b98bea68e8ce31ed5ae32485119dd5c24612d087fa5110129b7c8429d0d96a65"
        },
        {
            "mediaType": "application/vnd.docker.image.rootfs.diff.tar.gzip",
            "size": 3310349,
            "digest": "sha256:03ac043af787c8cb06d6a7f8289c62cf97e630b08011717197ab2adb087d061d"
        }
    ]
}