{
    "schemaVersion": 2,
    "mediaType": "application/vnd.docker.distribution.manifest.v2+json",
    "config": {
        "mediaType": "application/vnd.docker.container.image.v1+json",
        "size": 2554,
        "digest": "sha256:a47ed91b1298b58acfb3cdf5f2e3bbdc8e8fc0f98910adc0108464631cf15582"
    },
    "layers": [
        {
            "mediaType": "application/vnd.docker.image.rootfs.diff.tar.gzip",
            "size": 100828703,
            "digest": "sha256:060999a19daa4d71c3fab5838fbb7d9f8df5e0fe68a30f95adacf9bc948afebf"
        },
        {
            "mediaType": "application/vnd.docker.image.rootfs.diff.tar.gzip",
            "size": 81506,
            "digest": "sha256:a1542687c0166fd2f786306c878381e78659a66ad48d79a25c37ea32a0886b16"
        },
        {
            "mediaType": "application/vnd.docker.image.rootfs.diff.tar.gzip",
            "size": 416,
            "digest": "sha256:f23662b7f21451ec379a83eaeb9338d092e1195609893330d62676200839bcb7"
        },
        {
            "mediaType": "application/vnd.docker.image.rootfs.diff.tar.gzip",
            "size": 2296235,
            "digest": "sha256:cbc023ce63975263ac3037a209069cec3e364cedbba9ccdeb668607ee9f2dd8f"
        }
    ]
}