{
    "schemaVersion": 2,
    "mediaType": "application/vnd.docker.distribution.manifest.v2+json",
    "config": {
        "mediaType": "application/vnd.docker.container.image.v1+json",
        "size": 2554,
        "digest": "sha256:91ecdb0468f6155293ef5b4cd111dfe10c892a907f67ea40e3b6644a6b4c8f0e"
    },
    "layers": [
        {
            "mediaType": "application/vnd.docker.image.rootfs.diff.tar.gzip",
            "size": 230643311,
            "digest": "sha256:d80d920e76e3210d9de57dffae0c65698c25e041dc3cb778fced1d5f5d872cf9"
        },
        {
            "mediaType": "application/vnd.docker.image.rootfs.diff.tar.gzip",
            "size": 84283,
            "digest": "sha256:ebb0a3ae5718d6864d28fefea60b682066c350bb2decfa0652d5040eb008f776"
        },
        {
            "mediaType": "application/vnd.docker.image.rootfs.diff.tar.gzip",
            "size": 416,
            "digest": "sha256:74d1cad19582e4b814e9bbd9019b25cd7695b35cd91d7369eb21ac30d95f9874"
        },
        {
            "mediaType": "application/vnd.docker.image.rootfs.diff.tar.gzip",
            "size": 2296235,
            "digest": "sha256:cbc023ce63975263ac3037a209069cec3e364cedbba9ccdeb668607ee9f2dd8f"
        }
    ]
}