{
    "schemaVersion": 2,
    "mediaType": "application/vnd.docker.distribution.manifest.v2+json",
    "config": {
        "mediaType": "application/vnd.docker.container.image.v1+json",
        "size": 2554,
        "digest": "sha256:ce312a4c8a392004d5c28820c3c0505aff36006076371ce7d89085a6fd7d1b92"
    },
    "layers": [
        {
            "mediaType": "application/vnd.docker.image.rootfs.diff.tar.gzip",
            "size": 326456972,
            "digest": "sha256:46d716cbbff63c548fecfa6441beca7920da16dfb26deed6e06dede86ce54e92"
        },
        {
            "mediaType": "application/vnd.docker.image.rootfs.diff.tar.gzip",
            "size": 81556,
            "digest": "sha256:313f7af6a01d98332966fdbd25f0d220bab3c168d01fbd86f94f3aef927b9b23"
        },
        {
            "mediaType": "application/vnd.docker.image.rootfs.diff.tar.gzip",
            "size": 416,
            "digest": "sha256:898fab034557f2016d55e8c5ae48499d60b3bc399326e6277e0b86079e725b3d"
        },
        {
            "mediaType": "application/vnd.docker.image.rootfs.diff.tar.gzip",
            "size": 2296235,
            "digest": "sha256:cbc023ce63975263ac3037a209069cec3e364cedbba9ccdeb668607ee9f2dd8f"
        }
    ]
}