{
    "schemaVersion": 2,
    "mediaType": "application/vnd.docker.distribution.manifest.list.v2+json",
    "manifests": [
        {
            "digest": "sha256:cbbbf1a2c8591c11853400fe7db1ce5741016c9f5f034ab57ea0289f675bc249",
            "mediaType": "application/vnd.docker.distribution.manifest.v2+json",
            "platform": {
                "architecture": "amd64",
                "os": "linux"
            },
            "size": 528
        },
        {
            "digest": "sha256:465ecee0e81c04ecc3ca5430a59dfe0b6e23097f0cba4b19147be4d982df1dea",
            "mediaType": "application/vnd.docker.distribution.manifest.v2+json",
            "platform": {
                "architecture": "arm",
                "os": "linux",
                "variant": "v6"
            },
            "size": 528
        },
        {
            "digest": "sha256:24b9d51104800c9e1dac1fec7299eec20cf40a98cbe0111b0f46d3e61367caea",
            "mediaType": "application/vnd.docker.distribution.manifest.v2+json",
            "platform": {
                "architecture": "arm",
                "os": "linux",
                "variant": "v7"
            },
            "size": 528
        },
        {
            "digest": "sha256:c677bb308d501faf2f972113e211b62a502f9d26e5ac2c6b2ce12ed841f6f4e1",
            "mediaType": "application/vnd.docker.distribution.manifest.v2+json",
            "platform": {
                "architecture": "arm64",
                "os": "linux",
                "variant": "v8"
            },
            "size": 528
        },
        {
            "digest": "sha256:2880ac0f2a3849b73c2419720169efde00d348c5cfe34bbcad401422cb70a7bf",
            "mediaType": "application/vnd.docker.distribution.manifest.v2+json",
            "platform": {
                "architecture": "386",
                "os": "linux"
            },
            "size": 528
        },
        {
            "digest": "sha256:9479acbbc4bad03b6043707760460f493b1acf9c6dc60df120d577967157098b",
            "mediaType": "application/vnd.docker.distribution.manifest.v2+json",
            "platform": {
                "architecture": "ppc64le",
                "os": "linux"
            },
            "size": 528
        },
        {
            "digest": "sha256:864d94acc76d855fffab052ad1a7fefe227f21acf2f11c29c2cbd1c13b21d5ba",
            "mediaType": "application/vnd.docker.distribution.manifest.v2+json",
            "platform": {
                "architecture": "s390x",
                "os": "linux"
            },
            "size": 528
        }
    ]
}